pyspark_cbor/__init__.py
pyspark_cbor/parsers.py
pyspark_cbor/py.typed
pyspark_cbor-0.1.2.dist-info/METADATA
pyspark_cbor-0.1.2.dist-info/WHEEL
pyspark_cbor-0.1.2.dist-info/RECORD
