Metadata-Version: 2.4
Name: pyspark-cbor
Version: 0.1.2
Summary: Reading and writing CBOR files with PySpark
Author-email: Daniël Tom <d.e.tom89@gmail.com>
Requires-Python: >=3.9
Requires-Dist: cbor2>=5.6.5
